daqmx/__init__.py
daqmx/daqmx.py
daqmx-0.4.4.dist-info/METADATA
daqmx-0.4.4.dist-info/WHEEL
daqmx-0.4.4.dist-info/top_level.txt
daqmx-0.4.4.dist-info/zip-safe
daqmx-0.4.4.dist-info/RECORD
