Metadata-Version: 2.1
Name: daqmx
Version: 0.4.4
Summary: DAQ control using National Instruments DAQmx framework
Home-page: https://github.com/slightlynybbled/daqmx
Author: Jason R. Jones
Author-email: slightlynybbled@gmail.com
License: MIT
Keywords: nationalinstruments,national,instruments,national instruments,daqmx,nidaqmx,daq,data acquisition,usb-6001
Platform: UNKNOWN
Classifier: Development Status :: 4 - Beta
Classifier: Programming Language :: Python :: 3
Classifier: Programming Language :: Python :: 3.6
Classifier: Programming Language :: Python :: 3.7
Classifier: Programming Language :: Python :: 3.8
Classifier: Natural Language :: English
Requires-Python: >=3.6.0
Requires-Dist: numpy (>=1.19.4)
Requires-Dist: pydaqmx (>=1.4.4)
